gym_janggi/__init__.py
gym_janggi/constants.py
gym_janggi/play.py
gym_janggi/utils.py
gym_janggi/envs/__init__.py
gym_janggi/envs/janggi.py
gym_janggi-0.9.24.dist-info/LICENSE
gym_janggi-0.9.24.dist-info/METADATA
gym_janggi-0.9.24.dist-info/WHEEL
gym_janggi-0.9.24.dist-info/top_level.txt
gym_janggi-0.9.24.dist-info/RECORD
