Metadata-Version: 2.1
Name: gym-janggi
Version: 0.9.24
Summary: OpenAI Gym environment for Korean chess Janggi
Home-page: https://github.com/sungho-cho/gym-janggi
Author: Sungho Cho
Author-email: didog9595@gmail.com
Classifier: Programming Language :: Python :: 3
Classifier: License :: OSI Approved :: GNU General Public License v3 or later (GPLv3+)
Classifier: Operating System :: OS Independent
Requires-Python: >=3.6
License-File: LICENSE
Requires-Dist: gym (==0.23.1)
Requires-Dist: janggi (==1.0.5)
